withsecure/__init__.py
withsecure/client.py
withsecure/control.py
withsecure/exceptions.py
withsecure/representation/__init__.py
withsecure/representation/device.py
withsecure/representation/incident.py
withsecure/representation/organization.py
withsecure_elements_api-0.1.1.dist-info/METADATA
withsecure_elements_api-0.1.1.dist-info/WHEEL
withsecure_elements_api-0.1.1.dist-info/entry_points.txt
withsecure_elements_api-0.1.1.dist-info/licenses/LICENSE
withsecure_elements_api-0.1.1.dist-info/RECORD
