Metadata-Version: 2.4
Name: withsecure-elements-api
Version: 0.1.1
Author-Email: y0no <contact@y0no.fr>
License-Expression: GPL-3.0-or-later
License-File: LICENSE
Classifier: Programming Language :: Python :: 3
Classifier: Operating System :: OS Independent
Classifier: Programming Language :: Python
Project-URL: Repository, https://github.com/Attineos-Cyber/withsecure-elements-api
Project-URL: Issues, https://github.com/Attineos-Cyber/withsecure-elements-api/issues
Requires-Python: >=3.9
Requires-Dist: dataclasses-json==0.6.7
Requires-Dist: requests>=2.31
Requires-Dist: python-dateutil>=2.9.0.post0
